{
  "index_name": "developer-portal",
  "start_urls": [
    "https://developers.cardano.org/docs/get-started/",
    "https://developers.cardano.org/docs/integrate-cardano/",
    "https://developers.cardano.org/docs/transaction-metadata/",
    "https://developers.cardano.org/docs/native-tokens/",
    "https://developers.cardano.org/docs/smart-contracts/",
    "https://developers.cardano.org/docs/fund-your-project/",
    "https://developers.cardano.org/docs/operate-a-stake-pool/",
    "https://developers.cardano.org/tools",
    "https://developers.cardano.org/showcase",
    "https://developers.cardano.org/blog/"
  ],
  "sitemap_urls": [
    "https://developers.cardano.org/sitemap.xml"
  ],
  "sitemap_alternate_links": true,
  "stop_urls": [],
  "selectors": {
     "lvl0": {
      "selector": "(//ul[contains(@class,'menu__list')]//a[contains(@class, 'menu__link menu__link--sublist menu__link--active')]/text() | //nav[contains(@class, 'navbar')]//a[contains(@class, 'navbar__link--active')]/text())[last()]",
      "type": "xpath",
      "global": true,
      "default_value": "Documentation"
    },
    "lvl1": "header h1",
    "lvl2": "article h2",
    "lvl3": "article h3",
    "lvl4": "article h4",
    "lvl5": "article h5, article td:first-child",
    "lvl6": "article h6",
    "text": "article p, article li, article td:last-child"
  },
  "strip_chars": " .,;:#",
  "custom_settings": {
    "separatorsToIndex": "_",
    "attributesForFaceting": [
      "language",
      "version",
      "type",
      "docusaurus_tag"
    ],
    "attributesToRetrieve": [
      "hierarchy",
      "content",
      "anchor",
      "url",
      "url_without_anchor",
      "type"
    ]
  },
  "conversation_id": [
    "1417357410"
  ],
  "nb_hits": 900
}